proqsar/__init__.py
proqsar/__main__.py
proqsar/data_generator.py
proqsar/data_preprocessor.py
proqsar/infer.py
proqsar/optimal_dataset.py
proqsar/qsar.py
proqsar/Config/config.py
proqsar/Config/debug.py
proqsar/Config/validation_config.py
proqsar/Data/__init__.py
proqsar/Data/Featurizer/PubChem.py
proqsar/Data/Featurizer/__init__.py
proqsar/Data/Featurizer/feature_generator.py
proqsar/Data/Featurizer/featurizer_wrapper.py
proqsar/Data/Splitter/__init__.py
proqsar/Data/Splitter/butina_splitter.py
proqsar/Data/Splitter/data_splitter.py
proqsar/Data/Splitter/random_scaffold_splitter.py
proqsar/Data/Splitter/random_splitter.py
proqsar/Data/Splitter/scaffold_splitter.py
proqsar/Data/Splitter/scaffold_utils.py
proqsar/Data/Splitter/stratified_random_splitter.py
proqsar/Data/Splitter/stratified_scaffold_kfold.py
proqsar/Data/Splitter/stratified_scaffold_splitter.py
proqsar/Data/Standardizer/__init__.py
proqsar/Data/Standardizer/smiles_standardizer.py
proqsar/Data/Standardizer/standardizer_wrapper.py
proqsar/Evaluation/__init__.py
proqsar/Evaluation/applicability_domain.py
proqsar/Evaluation/conformal_predictor.py
proqsar/Evaluation/statistical_analysis.py
proqsar/Model/__init__.py
proqsar/Model/FeatureSelector/__init__.py
proqsar/Model/FeatureSelector/feature_selector.py
proqsar/Model/FeatureSelector/feature_selector_utils.py
proqsar/Model/ModelDeveloper/__init__.py
proqsar/Model/ModelDeveloper/model_developer.py
proqsar/Model/ModelDeveloper/model_developer_utils.py
proqsar/Model/ModelDeveloper/model_validation.py
proqsar/Model/Optimizer/__init__.py
proqsar/Model/Optimizer/optimizer.py
proqsar/Model/Optimizer/optimizer_utils.py
proqsar/Preprocessor/__init__.py
proqsar/Preprocessor/Clean/__init__.py
proqsar/Preprocessor/Clean/duplicate_handler.py
proqsar/Preprocessor/Clean/low_variance_handler.py
proqsar/Preprocessor/Clean/missing_handler.py
proqsar/Preprocessor/Clean/rescaler.py
proqsar/Preprocessor/Outlier/__init__.py
proqsar/Preprocessor/Outlier/kbin_handler.py
proqsar-0.0.9.dist-info/METADATA
proqsar-0.0.9.dist-info/WHEEL
proqsar-0.0.9.dist-info/licenses/LICENSE
proqsar-0.0.9.dist-info/RECORD
