Metadata-Version: 2.4
Name: proqsar
Version: 0.0.9
Summary: ProQSAR — automation utilities for QSAR workflows (standardization, featurization, model building & evaluation).
Project-URL: homepage, https://github.com/Medicine-Artificial-Intelligence/ProQSAR
Project-URL: source, https://github.com/Medicine-Artificial-Intelligence/ProQSAR
Project-URL: issues, https://github.com/Medicine-Artificial-Intelligence/ProQSAR/issues
Project-URL: documentation, https://proqsar.readthedocs.io/en/latest/
Author-email: Tuyet Minh Phan <minh@bioinf.uni-leipzig.de>, Tieu Long Phan <tieu@bioinf.uni-leipzig.de>
License: MIT
License-File: LICENSE
Classifier: Development Status :: 4 - Beta
Classifier: Intended Audience :: Science/Research
Classifier: License :: OSI Approved :: MIT License
Classifier: Operating System :: OS Independent
Classifier: Programming Language :: Python :: 3
Classifier: Programming Language :: Python :: 3 :: Only
Classifier: Topic :: Scientific/Engineering :: Bio-Informatics
Requires-Python: >=3.11
Requires-Dist: catboost==1.2.7
Requires-Dist: joblib==1.4.2
Requires-Dist: mapie==0.9.2
Requires-Dist: matplotlib==3.9.2
Requires-Dist: numpy==1.26.4
Requires-Dist: optuna==4.0.0
Requires-Dist: pandas==2.2.2
Requires-Dist: pingouin==0.5.5
Requires-Dist: rdkit==2025.03.1
Requires-Dist: scikit-learn==1.5.1
Requires-Dist: scikit-posthocs==0.11.2
Requires-Dist: scipy==1.14.1
Requires-Dist: seaborn==0.13.2
Requires-Dist: statsmodels==0.14.4
Requires-Dist: xgboost==2.1.1
Provides-Extra: all
Requires-Dist: mordred==1.2.0; extra == 'all'
Provides-Extra: dev
Requires-Dist: black>=24.9; extra == 'dev'
Requires-Dist: mypy>=1.8; extra == 'dev'
Requires-Dist: pre-commit; extra == 'dev'
Requires-Dist: pytest>=7.4; extra == 'dev'
Requires-Dist: ruff>=0.1; extra == 'dev'
Requires-Dist: towncrier; extra == 'dev'
Provides-Extra: docs
Requires-Dist: sphinx-rtd-theme; extra == 'docs'
Requires-Dist: sphinx>=6.0; extra == 'docs'
Requires-Dist: sphinxcontrib-bibtex; extra == 'docs'
Provides-Extra: ml
Requires-Dist: catboost==1.2.7; extra == 'ml'
Requires-Dist: lightgbm>=4.0.0; extra == 'ml'
Requires-Dist: xgboost==2.1.1; extra == 'ml'
Provides-Extra: viz
Requires-Dist: plotly>=5.0.0; extra == 'viz'
Requires-Dist: seaborn==0.13.2; extra == 'viz'
